oauth2handler/__init__.py
oauth2handler/cli.py
oauth2handler/exceptions.py
oauth2handler/oauth2_client.py
oauth2handler/utils.py
oauth2handler-0.1.1.dist-info/licenses/LICENSE
oauth2handler-0.1.1.dist-info/METADATA
oauth2handler-0.1.1.dist-info/WHEEL
oauth2handler-0.1.1.dist-info/entry_points.txt
oauth2handler-0.1.1.dist-info/top_level.txt
oauth2handler-0.1.1.dist-info/RECORD
