Metadata-Version: 2.4
Name: oauth2handler
Version: 0.1.1
Summary: A simple OAuth2 client for developers
Home-page: https://github.com/Tomer-Barak/oauth2handler
Author: OAuth2 Handler Contributors
Author-email: tomer.barak.mail@gmail.com
License: MIT
Project-URL: Bug Tracker, https://github.com/Tomer-Barak/oauth2handler/issues
Project-URL: Source Code, https://github.com/Tomer-Barak/oauth2handler
Classifier: Programming Language :: Python :: 3
Classifier: Programming Language :: Python :: 3.6
Classifier: Programming Language :: Python :: 3.7
Classifier: Programming Language :: Python :: 3.8
Classifier: Programming Language :: Python :: 3.9
Classifier: Programming Language :: Python :: 3.10
Classifier: License :: OSI Approved :: MIT License
Classifier: Operating System :: OS Independent
Classifier: Development Status :: 4 - Beta
Classifier: Intended Audience :: Developers
Classifier: Topic :: Software Development :: Libraries :: Python Modules
Requires-Python: >=3.6
License-File: LICENSE
Requires-Dist: requests>=2.25.0
Dynamic: author
Dynamic: author-email
Dynamic: classifier
Dynamic: description
Dynamic: description-content-type
Dynamic: home-page
Dynamic: license
Dynamic: license-file
Dynamic: project-url
Dynamic: requires-dist
Dynamic: requires-python
Dynamic: summary
